{
    "imageURL": "/img/tiles.png",
    "tileW": 16,
    "tileH": 16,
    "tiles": [
        {
            "name": "ground",
            "index": [0, 4]
        },
        {
            "name": "sky",
            "index": [13, 3]
        },
        {
            "name": "chocolate",
            "index": [0, 5]
        },
        {
            "name": "bricks",
            "index": [1, 4]
        },
        {
            "name": "chance",
            "index": [24, 4]
        },
        {
            "name": "chance-1",
            "index": [24, 4]
        },
        {
            "name": "chance-2",
            "index": [25, 4]
        },
        {
            "name": "chance-3",
            "index": [26, 4]
        }
    ],
    "animations": [
        {
            "name": "chance",
            "frameLen": 0.14,
            "frames": [
                "chance-1",
                "chance-1",
                "chance-2",
                "chance-3",
                "chance-2"
            ]
        }
    ]
}